tibia_ocr/__init__.py
tibia_ocr/constants.py
tibia_ocr/exceptions.py
tibia_ocr/hash_ocr.py
tibia_ocr/py.typed
tibia_ocr/shortcuts.py
tibia_ocr/train.py
tibia_ocr/utils.py
tibia_ocr/fonts/big.json
tibia_ocr/fonts/small.json
tibia_ocr/fonts/small_a.json
tibia_ocr-1.0.8.dist-info/LICENSE
tibia_ocr-1.0.8.dist-info/METADATA
tibia_ocr-1.0.8.dist-info/WHEEL
tibia_ocr-1.0.8.dist-info/top_level.txt
tibia_ocr-1.0.8.dist-info/RECORD
