Metadata-Version: 2.1
Name: tibia-ocr
Version: 1.0.8
Summary: OCR to read Tibia in-game text written in python
Home-page: https://github.com/sandbox-pokhara/tibia-ocr
Author: Pradish Bijukchhe
Author-email: pradishbijukchhe@gmail.com
Project-URL: Bug Tracker, https://github.com/sandbox-pokhara/tibia-ocr/issues
Classifier: Programming Language :: Python :: 3
Classifier: License :: OSI Approved :: MIT License
Requires-Python: >=3
License-File: LICENSE
Requires-Dist: opencv-python
